msmart/__init__.py
msmart/base_device.py
msmart/cli.py
msmart/cloud.py
msmart/const.py
msmart/crc8.py
msmart/discover.py
msmart/frame.py
msmart/lan.py
msmart/utils.py
msmart/device/__init__.py
msmart/device/AC/__init__.py
msmart/device/AC/command.py
msmart/device/AC/device.py
msmart/device/AC/test_command.py
msmart/device/AC/test_device.py
GT3CH1_msmart_ng-0.0.2.dist-info/LICENSE.md
GT3CH1_msmart_ng-0.0.2.dist-info/METADATA
GT3CH1_msmart_ng-0.0.2.dist-info/WHEEL
GT3CH1_msmart_ng-0.0.2.dist-info/entry_points.txt
GT3CH1_msmart_ng-0.0.2.dist-info/top_level.txt
GT3CH1_msmart_ng-0.0.2.dist-info/RECORD
