Metadata-Version: 2.1
Name: GT3CH1-msmart-ng
Version: 0.0.2
Summary: A Python library for local control of Midea (and associated brands) smart air conditioners.
Author-email: Tucker Kern <tuckkern@gmail.com>
License: MIT
Project-URL: Repository, https://github.com/mill1000/midea-msmart
Project-URL: Issues, https://github.com/mill1000/midea-msmart/issues
Classifier: Programming Language :: Python :: 3
Classifier: Programming Language :: Python :: 3.8
Classifier: Programming Language :: Python :: 3.9
Classifier: Programming Language :: Python :: 3.10
Classifier: Programming Language :: Python :: 3.11
Classifier: Programming Language :: Python :: 3.12
Classifier: License :: OSI Approved :: MIT License
Classifier: Operating System :: OS Independent
Classifier: Topic :: Home Automation
Requires-Python: >=3.8
License-File: LICENSE.md
Requires-Dist: pycryptodome
Requires-Dist: httpx
